README.md
setup.py
kerosene/__init__.py
kerosene/configs/__init__.py
kerosene/configs/configs.py
kerosene/configs/exceptions.py
kerosene/configs/parsers.py
kerosene/events/__init__.py
kerosene/events/exceptions.py
kerosene/events/handlers/__init__.py
kerosene/events/handlers/base_handler.py
kerosene/events/handlers/base_monitor_watcher.py
kerosene/events/handlers/checkpoints.py
kerosene/events/handlers/console.py
kerosene/events/handlers/early_stopping.py
kerosene/events/handlers/visdom.py
kerosene/events/publishers/__init__.py
kerosene/events/publishers/base_publisher.py
kerosene/loggers/__init__.py
kerosene/loggers/visdom/__init__.py
kerosene/loggers/visdom/config.py
kerosene/loggers/visdom/data.py
kerosene/loggers/visdom/plots.py
kerosene/loggers/visdom/visdom.py
kerosene/metrics/__init__.py
kerosene/metrics/gauges.py
kerosene/metrics/metrics.py
kerosene/models/__init__.py
kerosene/models/models.py
kerosene/nn/__init__.py
kerosene/nn/apex.py
kerosene/nn/criterions.py
kerosene/nn/functional.py
kerosene/nn/utils/__init__.py
kerosene/nn/utils/gradients.py
kerosene/optim/__init__.py
kerosene/optim/optimizers.py
kerosene/optim/schedulers.py
kerosene/training/__init__.py
kerosene/training/events.py
kerosene/training/trainers.py
kerosene/utils/__init__.py
kerosene/utils/configs.py
kerosene/utils/constants.py
kerosene/utils/devices.py
kerosene/utils/files.py
kerosene/utils/tensors.py
tests/configs/__init__.py
tests/configs/test_model_trainers_config.py
tests/events/__init__.py
tests/events/handlers/__init__.py
tests/events/handlers/test_checkpoints.py
tests/events/handlers/test_console.py
tests/events/handlers/test_early_stopping.py
tests/events/handlers/test_visdom.py
tests/events/publishers/__init__.py
tests/functionals/__init__.py
tests/functionals/models.py
tests/functionals/distributed/__init__.py
tests/functionals/distributed/main.py
tests/functionals/distributed/mnist_trainer.py
tests/loggers/__init__.py
tests/loggers/visdom/__init__.py
torch_kerosene.egg-info/PKG-INFO
torch_kerosene.egg-info/SOURCES.txt
torch_kerosene.egg-info/dependency_links.txt
torch_kerosene.egg-info/requires.txt
torch_kerosene.egg-info/top_level.txt