Metadata-Version: 2.1
Name: torch-kerosene
Version: 0.2.1
Summary: Deep Learning framework for fast and clean research development with Pytorch
Home-page: UNKNOWN
Author: Benoit Anctil-Robitaille
Author-email: benoit.anctil-robitaille.1@ens.etsmtl.ca
License: MIT
Platform: UNKNOWN
Classifier: License :: OSI Approved :: MIT License
Classifier: Programming Language :: Python :: 3
Classifier: Programming Language :: Python :: 3.7
